pygeode/toolscore.cpython-39-x86_64-linux-gnu.so
pygeode/intgr.py
pygeode/timeaxiscore.cpython-39-x86_64-linux-gnu.so
pygeode/svdcore.cpython-39-x86_64-linux-gnu.so
pygeode/progress.py
pygeode/eof.py
pygeode/fft_smooth.py
pygeode/deriv.py
pygeode/tutorial.py
pygeode/ufunc.py
pygeode/axis.py
pygeode/eofcore.cpython-39-x86_64-linux-gnu.so
pygeode/libhelper.py
pygeode/timeticker.py
pygeode/spectral.py
pygeode/interp.py
pygeode/interpcore.cpython-39-x86_64-linux-gnu.so
pygeode/pygrc
pygeode/diff.py
pygeode/varoperations.py
pygeode/svd.py
pygeode/__init__.py
pygeode/var.py
pygeode/timeaxis.py
pygeode/s_trans2.py
pygeode/quadrulepy.cpython-39-x86_64-linux-gnu.so
pygeode/data.py
pygeode/_version.py
pygeode/composite.py
pygeode/ensemble.py
pygeode/smooth.py
pygeode/ext_xarray.py
pygeode/concat.py
pygeode/view.py
pygeode/reduce.py
pygeode/dataset.py
pygeode/stats.py
pygeode/timeutils.py
pygeode/tools.py
pygeode/climat.py
pygeode/server/__init__.py
pygeode/server/daemon.py
pygeode/server/web.py
pygeode/options/immediate_evaluation.py
pygeode/options/__init__.py
pygeode/formats/data_scanner.py
pygeode/formats/cfmeta.py
pygeode/formats/opendap.py
pygeode/formats/hdf4.py
pygeode/formats/mpeg.py
pygeode/formats/grib.py
pygeode/formats/multifile.py
pygeode/formats/__init__.py
pygeode/formats/opendapcore.cpython-39-x86_64-linux-gnu.so
pygeode/formats/netcdf.py
pygeode/formats/gribcore.cpython-39-x86_64-linux-gnu.so
pygeode/formats/netcdf4.py
pygeode/plot/plot_v1.py
pygeode/plot/basemap.py
pygeode/plot/pyg_helpers.py
pygeode/plot/wrappers.py
pygeode/plot/cm.py
pygeode/plot/__init__.py
pygeode/plot/cartopy.py
pygeode/plot/cnt_helpers.py
pygeode/plugins/__init__.py
pygeode-1.4.1.dist-info/LICENSE
pygeode-1.4.1.dist-info/RECORD
pygeode-1.4.1.dist-info/METADATA
pygeode-1.4.1.dist-info/WHEEL
pygeode-1.4.1.dist-info/top_level.txt
pygeode.libs/liblapack-7aef6c42.so.3.0
pygeode.libs/libcblas-70dd3697.so.3.0
pygeode.libs/libgsl-84259690.so.0.14.0
pygeode.libs/libgfortran-139be63a.so.3.0.0
pygeode.libs/libf77blas-75a5c7e0.so.3.0
pygeode.libs/libgslcblas-f2b9007c.so.0.0.0
