Metadata-Version: 2.1
Name: pygeode
Version: 1.4.1
Summary: Gridded data manipulator for Python
Home-page: http://pygeode.github.io
Author: Peter Hitchcock, Andre Erler, Mike Neish
Author-email: pygeode-users@googlegroups.com
License: GPL-3
Platform: UNKNOWN
License-File: LICENSE
Requires-Dist: numpy
Requires-Dist: scipy
Requires-Dist: matplotlib
Requires-Dist: progressbar2
Requires-Dist: netcdf4
